{
  "trajectories": {
    "B2T_R": {
      "meta": {
        "generated_from": "B2T_R",
        "ops": [],
        "source_hash": "manual"
      },
      "anchors": [
        {
          "id": "CO_(65,-2.25)_50"
        },
        {
          "id": "CO_(70,-2.25)_70"
        },
        {
          "id": "CO_(75,-2.25)_90"
        },
        {
          "id": "1C_(81.5,40)_0"
        },
        {
          "id": "1C_(81.5,35)_10"
        },
        {
          "id": "1C_(81.5,30)_20"
        },
        {
          "id": "1C_(81.5,25)_30"
        },
        {
          "id": "1C_(81.5,20)_40"
        },
        {
          "id": "1C_(81.5,15)_50"
        },
        {
          "id": "4C_(79,0)_50"
        },
        {
          "id": "4C_(72.5,0)_70"
        },
        {
          "id": "4C_(67.5,0)_90"
        }
      ]
    },
    "B2T_L": {
      "meta": {
        "generated_from": "B2T_L",
        "ops": [],
        "source_hash": "manual"
      },
      "anchors": [
        {
          "id": "CO_(15,-2.25)_50"
        },
        {
          "id": "CO_(10,-2.25)_70"
        },
        {
          "id": "CO_(5,-2.25)_90"
        },
        {
          "id": "1C_(-1.5,40)_0"
        },
        {
          "id": "1C_(-1.5,35)_10"
        },
        {
          "id": "1C_(-1.5,30)_20"
        },
        {
          "id": "1C_(-1.5,25)_30"
        },
        {
          "id": "1C_(-1.5,20)_40"
        },
        {
          "id": "1C_(-1.5,15)_50"
        },
        {
          "id": "4C_(1,0)_50"
        },
        {
          "id": "4C_(7.5,0)_70"
        },
        {
          "id": "4C_(12.5,0)_90"
        }
      ]
    },
    "T2B_R": {
      "meta": {
        "generated_from": "T2B_R",
        "ops": [],
        "source_hash": "manual"
      },
      "anchors": [
        {
          "id": "CO_(15,42.25)_50"
        },
        {
          "id": "CO_(10,42.25)_70"
        },
        {
          "id": "CO_(5,42.25)_90"
        },
        {
          "id": "1C_(-1.5,0)_0"
        },
        {
          "id": "1C_(-1.5,5)_10"
        },
        {
          "id": "1C_(-1.5,10)_20"
        },
        {
          "id": "1C_(-1.5,15)_30"
        },
        {
          "id": "1C_(-1.5,20)_40"
        },
        {
          "id": "1C_(-1.5,25)_50"
        },
        {
          "id": "4C_(1,40)_50"
        },
        {
          "id": "4C_(7.5,40)_70"
        },
        {
          "id": "4C_(12.5,40)_90"
        }
      ]
    },
    "T2B_L": {
      "meta": {
        "generated_from": "T2B_L",
        "ops": [],
        "source_hash": "manual"
      },
      "anchors": [
        {
          "id": "CO_(65,42.25)_50"
        },
        {
          "id": "CO_(70,42.25)_70"
        },
        {
          "id": "CO_(75,42.25)_90"
        },
        {
          "id": "1C_(81.5,0)_0"
        },
        {
          "id": "1C_(81.5,5)_10"
        },
        {
          "id": "1C_(81.5,10)_20"
        },
        {
          "id": "1C_(81.5,15)_30"
        },
        {
          "id": "1C_(81.5,20)_40"
        },
        {
          "id": "1C_(81.5,25)_50"
        },
        {
          "id": "4C_(79,40)_50"
        },
        {
          "id": "4C_(72.5,40)_70"
        },
        {
          "id": "4C_(67.5,40)_90"
        }
      ]
    }
  }
}